texted/__init__.py
texted/_edit.py
texted/_predicate.py
texted/_single_selection.py
texted/_version.py
texted/py.typed
texted-0b1.dist-info/AUTHORS.rst
texted-0b1.dist-info/LICENSE.txt
texted-0b1.dist-info/METADATA
texted-0b1.dist-info/WHEEL
texted-0b1.dist-info/top_level.txt
texted-0b1.dist-info/RECORD
