Metadata-Version: 2.1
Name: texted
Version: 0b1
Summary: Compact DST for editing blocks of plain text
Author-email: Anderson Bravalheri <andersonbravalheri@gmail.com>
License: MPL-2.0
Project-URL: Homepage, https://github.com/pyscaffold/texted/
Project-URL: Documentation, https://texted.readthedocs.io/en/latest/
Project-URL: Changelog, https://texted.readthedocs.io/en/latest/changelog.html
Project-URL: Tracker, https://github.com/pyscaffold/texted/issues
Project-URL: Download, https://pypi.org/project/texted/#files
Classifier: Development Status :: 4 - Beta
Classifier: Programming Language :: Python
Requires-Python: >=3.7
License-File: LICENSE.txt
License-File: AUTHORS.rst
Requires-Dist: importlib-metadata ; python_version < "3.8"
Provides-Extra: testing
Requires-Dist: setuptools ; extra == 'testing'
Requires-Dist: pytest ; extra == 'testing'
Requires-Dist: pytest-cov ; extra == 'testing'
